sbook/__init__.py
sbook/epub_tool.py
sbook/json2epub.py
sbook/syncmeta.py
sbook/txt2epub.py
sbook/core/__init__.py
sbook/core/book.py
sbook/core/cover.py
sbook/static/DouyinSansBold.otf
sbook/static/hanyiyoukaifanti.ttf
sbook/static/stylesheet.css
sbook-0.0.11.dist-info/METADATA
sbook-0.0.11.dist-info/WHEEL
sbook-0.0.11.dist-info/entry_points.txt
sbook-0.0.11.dist-info/top_level.txt
sbook-0.0.11.dist-info/RECORD
