Metadata-Version: 2.4
Name: sbook
Version: 0.0.11
Summary: sbook
Author-email: Seven <1162584980@qq.com>
Maintainer-email: Seven <1162584980@qq.com>
License-Expression: MIT
Classifier: Environment :: Console :: Curses
Classifier: Operating System :: OS Independent
Classifier: Programming Language :: Python :: 3
Classifier: Topic :: Utilities
Requires-Python: >=3.11
Requires-Dist: ebooklib
Requires-Dist: Pillow
Requires-Dist: beautifulsoup4
Requires-Dist: requests
Requires-Dist: typer
Requires-Dist: rich
Requires-Dist: pydantic
Provides-Extra: dev
Requires-Dist: build; extra == "dev"
Requires-Dist: twine; extra == "dev"
